{
  "vendor":{
    "bootstrap": "node_modules/bootstrap-sass/assets/stylesheets/**/*"
  },
  "src" : {
    "ts"  : "./src/ts",
    "sass": "./src/sass"
  },
  "dist": {
    "js" : "./dist/js",
    "css": "./dist/css"
  },

  "node_modules": {
    "gulp"       : "gulp",
    "tsify"      : "tsify",
    "watchify"   : "watchify",
    "sass"       : "gulp-sass",
    "gutil"      : "gulp-util",
    "browserify" : "browserify",
    "shell"      : "gulp-shell",
    "watch"      : "gulp-watch",
    "concat"     : "gulp-concat",
    "uglify"     : "gulp-uglify",
    "buffer"     : "vinyl-buffer",
    "filesize"   : "gulp-filesize",
    "sourcemaps" : "gulp-sourcemaps",
    "ts"         : "gulp-typescript",
    "source"     : "vinyl-source-stream"
  }
}
